MANIFEST.in
README.md
setup.py
ros_translator.egg-info/PKG-INFO
ros_translator.egg-info/SOURCES.txt
ros_translator.egg-info/dependency_links.txt
ros_translator.egg-info/requires.txt
ros_translator.egg-info/top_level.txt
translator/__init__.py
translator/requirements.txt
translator/ros/a
translator/ros/plugin.py
translator/ros/lib/bionames.py
translator/ros/lib/biothings.py
translator/ros/lib/gamma.py
translator/ros/lib/graphoperator.py
translator/ros/lib/icees.py
translator/ros/lib/ndex.py
translator/ros/lib/xray.py
translator/ros/workflows/bionames.ros
translator/ros/workflows/grapherator_v1.ros
translator/ros/workflows/grapherator_v2.ros
translator/ros/workflows/green-cqs.ros
translator/ros/workflows/green_mq.txt
translator/ros/workflows/workflow_one.ros
translator/ros/workflows/workflow_one_tias.ros
translator/ros/workflows/workflow_one_tias_v1.ros
translator/ros/workflows/workflow_one_tias_v2.ros
translator/ros/workflows/workflow_one_tias_v3.ros