Metadata-Version: 2.1
Name: ros-translator
Version: 0.115
Summary: NCATS Translator Knowledge Network Workflow Engine
Home-page: http://github.com/NCATS-Tangerine/ros-translator.git
Author: Steve Cox
Author-email: scox@renci.org
License: UNKNOWN
Download-URL: http://github.com/NCATS-Tangerine/ros-translator/archive/0.001.tar.gz
Keywords: knowledge,network,graph,biomedical
Platform: UNKNOWN
